COPYING
MANIFEST.in
README.rst
distribute_setup.py
setup.py
doc/about.html
doc/index.html
doc/install.html
doc/markdown.html
doc/start.html
doc/todo.html
doc/css/bootstrap-responsive.css
doc/css/bootstrap-responsive.min.css
doc/css/bootstrap.css
doc/css/bootstrap.min.css
doc/img/glyphicons-halflings-white.png
doc/img/glyphicons-halflings.png
doc/jinja2/index.html
doc/js/bootstrap.js
doc/js/bootstrap.min.js
doc/js/jquery-1.8.3.min.js
doc/markdown/extensions.html
doc/markdown/markdown.html
doc/markdown/template.html
doc/rst/cheatsheet.html
doc/rst/quickref.html
doc/rst/rst.html
doc_src/about.rst
doc_src/index.html
doc_src/install.md
doc_src/start.md
doc_src/todo.md
doc_src/css/bootstrap-responsive.css
doc_src/css/bootstrap-responsive.min.css
doc_src/css/bootstrap.css
doc_src/css/bootstrap.min.css
doc_src/img/glyphicons-halflings-white.png
doc_src/img/glyphicons-halflings.png
doc_src/jinja2/index.md
doc_src/js/bootstrap.js
doc_src/js/bootstrap.min.js
doc_src/js/jquery-1.8.3.min.js
doc_src/markdown/extensions.md
doc_src/markdown/markdown.md
doc_src/markdown/template.md
doc_src/rst/cheatsheet.rst
doc_src/rst/quickref.html
doc_src/rst/rst.rst
doc_src/templates/base.html
doc_src/templates/markdown.html
linkdown/__init__.py
linkdown/convert.py
linkdown/datalist.txt
linkdown/htmlhelper.py
linkdown.egg-info/PKG-INFO
linkdown.egg-info/SOURCES.txt
linkdown.egg-info/dependency_links.txt
linkdown.egg-info/requires.txt
linkdown.egg-info/top_level.txt
linkdown/templates/Makefile
linkdown/templates/basic/about.md
linkdown/templates/basic/contacts.md
linkdown/templates/basic/index.html
linkdown/templates/basic/css/style.less
linkdown/templates/basic/img/header.png
linkdown/templates/basic/img/header.svg
linkdown/templates/basic/img/top.png
linkdown/templates/basic/img/top.svg
linkdown/templates/basic/js/hello.coffee
linkdown/templates/basic/templates/base.html
linkdown/templates/basic/templates/markdown.html
linkdown/templates/bootstrap/about.md
linkdown/templates/bootstrap/index.html
linkdown/templates/bootstrap/css/bootstrap-responsive.css
linkdown/templates/bootstrap/css/bootstrap-responsive.min.css
