Metadata-Version: 1.1
Name: linkdown
Version: 0.1.1
Summary: Build static webpages with Jinja2, Markdown, LESS, Coffeescript
Home-page: https://github.com/informationsea/linkdown
Author: Y.Okamura
Author-email: okamura@informationsea.info
License: GPL3+
Platform: UNKNOWN
Classifier: Development Status :: 3 - Alpha
Classifier: Operating System :: MacOS :: MacOS X
Classifier: Operating System :: Microsoft :: Windows
Classifier: Operating System :: POSIX
Classifier: Programming Language :: Python :: 2.7
Classifier: License :: OSI Approved :: GNU General Public License v3 or later (GPLv3+)
Classifier: Topic :: Internet :: WWW/HTTP :: Site Management
Classifier: Environment :: Web Environment
